{"DocumentId": "s3://ubc-scraped-courses/PSYC/306A.txt", "Attributes": {"_category": "PSYC", "courseNumber": "306A", "ubcURI": "https://courses.students.ubc.ca/cs/courseschedule?pname=subjarea&tname=subj-course&dept=PSYC&course=306A", "prereq": "Pre-reqs: Either (a) PSYC 100 or (b) two of PSYC 101, PSYC 102, PSYC 205, PSYC 207, PSYC 208, PSYC 216, PSYC 217, PSYC 277. (Strongly recommended: PSYC 101 and either PSYC 216 or one of PSYC 217 or 277.)", "credit": "3", "mode_of_delivery": "Online", "requires_in_person_attendance": "No", "instructor": "SEIB, DESIREE"}, "Title": "PSYC306A"}