{"DocumentId": "s3://ubc-scraped-courses/ASTU/310.txt", "Attributes": {"_category": "ASTU", "courseNumber": "310", "ubcURI": "https://courses.students.ubc.ca/cs/courseschedule?pname=subjarea&tname=subj-course&dept=ASTU&course=310", "description": "Approved and supervised work experience with a public or private organization for a minimum of 13 weeks full-time. Orientation workshops. Final work term report required. Restricted to students in the Arts Co-operative Education Program.", "prereq": "Pre-reqs: (6 credits first-year English or Arts I; 6 credits of science; 6 credits of literature; satisfaction of Faculty language requirement.)", "credit": "3", "mode_of_delivery": "In-Person", "requires_in_person_attendance": "Yes", "instructor": "TBA"}, "Title": "ASTU310"}