{"DocumentId": "s3://ubc-scraped-courses/DES/401.txt", "Attributes": {"_category": "DES", "courseNumber": "401", "ubcURI": "https://courses.students.ubc.ca/cs/courseschedule?pname=subjarea&tname=subj-course&dept=DES&course=401", "description": "Relationships between communities and environment, urban infrastructure and ecological systems.", "prereq": "Pre-reqs: DES 302.", "credit": "9", "mode_of_delivery": "In-Person", "requires_in_person_attendance": "Yes", "date_buildings": "Term: 1, Days: Mon Thu, Start Time: 13:30, End Time: 17:00\n", "instructor": "WATANABE, YUICHI"}, "Title": "DES401"}