{"DocumentId": "s3://ubc-scraped-courses/CONS/506.txt", "Attributes": {"_category": "CONS", "courseNumber": "506", "ubcURI": "https://courses.students.ubc.ca/cs/courseschedule?pname=subjarea&tname=subj-course&dept=CONS&course=506", "description": "Key forest conservation issues in Asia, regional strategies, programs, and practices for restoration of critical landscapes, rehabilitation of terrestrial ecosystems and conservation of flagship species.", "credit": "3", "mode_of_delivery": "Online", "requires_in_person_attendance": "No", "instructor": "WANG, GUANGYU"}, "Title": "CONS506"}