{"DocumentId": "s3://ubc-scraped-courses/ASIA/412.txt", "Attributes": {"_category": "ASIA", "courseNumber": "412", "ubcURI": "https://courses.students.ubc.ca/cs/courseschedule?pname=subjarea&tname=subj-course&dept=ASIA&course=412", "description": "Features and evolution of major pre-Chinese poetry from the 11th century B.C.E. to the 10th century C.E.; analytical reading of signature poems by selected poets in English translation in the pre-modern Chinese poetic tradition during this historical period.", "credit": "3", "mode_of_delivery": "Hybrid", "requires_in_person_attendance": "Yes", "date_buildings": "Term: 1, Days: Mon Wed, Start Time: 12:30, End Time: 14:00, Building: To, Room: Be\n", "instructor": "DUFFY, KAY JANE"}, "Title": "ASIA412"}