{"DocumentId": "s3://ubc-scraped-courses/GEOS/405.txt", "Attributes": {"_category": "GEOS", "courseNumber": "405", "ubcURI": "https://courses.students.ubc.ca/cs/courseschedule?pname=subjarea&tname=subj-course&dept=GEOS&course=405", "description": "Introduction to open channel flow and sediment transport. River morphology and channel types. Palaeohydrology. The development of channel networks.", "prereq": "Pre-reqs: One of EOSC 320, EOSC 330, GEOB 206, GEOS 206.", "credit": "3", "mode_of_delivery": "In-Person", "requires_in_person_attendance": "Yes", "instructor": "TBA"}, "Title": "GEOS405"}