{"DocumentId": "s3://ubc-scraped-courses/MIDW/101.txt", "Attributes": {"_category": "MIDW", "courseNumber": "101", "ubcURI": "https://courses.students.ubc.ca/cs/courseschedule?pname=subjarea&tname=subj-course&dept=MIDW&course=101", "description": "Theory, knowledge, strategies, and skills of person-centered counselling including family systems, trauma theory, theory, grief counselling, motivational interviewing skills, self-awareness and mindfulness, interprofessional communication, and cultural competency in continuity of care.", "credit": "3", "mode_of_delivery": "Hybrid", "requires_in_person_attendance": "Yes", "date_buildings": "Term: 1, Days: Wed, Start Time: 13:00, End Time: 16:00\n", "instructor": "CAMPBELL, MAGHAN"}, "Title": "MIDW101"}