{"DocumentId": "s3://ubc-scraped-courses/CPSC/103.txt", "Attributes": {"_category": "CPSC", "courseNumber": "103", "ubcURI": "https://courses.students.ubc.ca/cs/courseschedule?pname=subjarea&tname=subj-course&dept=CPSC&course=103", "description": "Computation as a tool for systematic problem solving in non-computer-science disciplines. Introductory programming skills. Not for credit for students who have credit for, or exemption from, or are concurrently taking CPSC 110 or APSC 160. No programming experience expected.", "credit": "3", "mode_of_delivery": "In-Person", "requires_in_person_attendance": "Yes", "date_buildings": "Term: 2, Days: Tue Thu, Start Time: 15:30, End Time: 17:00, Building: To, Room: Be\n", "instructor": "BLOK, HENDRIK"}, "Title": "CPSC103"}