{"DocumentId": "s3://ubc-scraped-courses/PATH/720.txt", "Attributes": {"_category": "PATH", "courseNumber": "720", "ubcURI": "https://courses.students.ubc.ca/cs/courseschedule?pname=subjarea&tname=subj-course&dept=PATH&course=720", "description": "Conduct of bacterial, fungal, parasitological, and viral laboratory tests relevant to the microbiological examination of patients. For medical residents.", "credit": "0", "mode_of_delivery": "In-Person", "requires_in_person_attendance": "Yes", "instructor": "TBA"}, "Title": "PATH720"}